dog_eye_diagnosis_mcp_server/__init__.py
dog_eye_diagnosis_mcp_server/__main__.py
dog_eye_diagnosis_mcp_server/server.py
dog_eye_diagnosis_mcp_server-1.2.5.dist-info/licenses/LICENSE
dog_eye_diagnosis_mcp_server-1.2.5.dist-info/METADATA
dog_eye_diagnosis_mcp_server-1.2.5.dist-info/WHEEL
dog_eye_diagnosis_mcp_server-1.2.5.dist-info/entry_points.txt
dog_eye_diagnosis_mcp_server-1.2.5.dist-info/top_level.txt
dog_eye_diagnosis_mcp_server-1.2.5.dist-info/RECORD
