Metadata-Version: 2.4
Name: dog-eye-diagnosis-mcp-server
Version: 1.2.5
Summary: A Model Context Protocol server analyzing dog's eye images and returning diagnosis probabilities for 10 diseases
Author: Jay Pak
Author-email: Jay Pak <jaypark@forestsoft.co.kr>
License: MIT
Classifier: Programming Language :: Python :: 3
Classifier: License :: OSI Approved :: MIT License
Classifier: Operating System :: OS Independent
Requires-Python: >=3.12
License-File: LICENSE
Requires-Dist: requests
Requires-Dist: pillow
Requires-Dist: mcp[cli]
Requires-Dist: pydantic
Dynamic: license-file
